tool.py
pyonenet/__init__.py
pyonenet-0.0.1.dist-info/METADATA
pyonenet-0.0.1.dist-info/WHEEL
pyonenet-0.0.1.dist-info/top_level.txt
pyonenet-0.0.1.dist-info/RECORD
