Metadata-Version: 2.1
Name: pyonenet
Version: 0.0.1
Summary: SDK for onenet
Home-page: UNKNOWN
Author: Xiao-qiao
Author-email: UNKNOWN
License: UNKNOWN
Platform: UNKNOWN
